trms/__init__.py
trms-0.2.4a1.dist-info/DESCRIPTION.rst
trms-0.2.4a1.dist-info/METADATA
trms-0.2.4a1.dist-info/RECORD
trms-0.2.4a1.dist-info/WHEEL
trms-0.2.4a1.dist-info/entry_points.txt
trms-0.2.4a1.dist-info/metadata.json
trms-0.2.4a1.dist-info/top_level.txt
