Metadata-Version: 2.0
Name: trms
Version: 0.2.4a1
Summary: Third-party Regis Moodle Scraper
Home-page: https://github.com/Apexal/trms
Author: Frank Matranga
Author-email: thefrankmatranga@gmail.com
License: MIT
Keywords: regis moodle scraper education school academics
Platform: UNKNOWN
Classifier: Development Status :: 3 - Alpha
Classifier: Intended Audience :: Developers
Classifier: License :: OSI Approved :: MIT License
Classifier: Programming Language :: Python :: 2
Requires-Dist: lxml
Requires-Dist: pymongo
Requires-Dist: requests
